iptoolbox/__init__.py
iptoolbox/data.json
iptoolbox/exceptions.py
iptoolbox/tools.py
iptoolbox/validation.py
iptoolbox-0.0.3.dist-info/LICENSE
iptoolbox-0.0.3.dist-info/METADATA
iptoolbox-0.0.3.dist-info/WHEEL
iptoolbox-0.0.3.dist-info/top_level.txt
iptoolbox-0.0.3.dist-info/RECORD
