Metadata-Version: 2.1
Name: iptoolbox
Version: 0.0.3
Summary: iptoolbox is a tool for purposefully creating IP, testing and scanning it
Home-page: https://github.com/V70024/iptoolbox
Author: V70024
Author-email: Zz2f0024@protonmail.com
License: MIT
Project-URL: Repository, https://github.com/V70024/iptoolbox/tree/0.0.3
Project-URL: Documentation, https://github.com/V70024/iptoolbox/wiki/iptoolbox-0.0.3
Project-URL: Bug Tracker, https://github.com/V70024/iptoolbox/issues
Keywords: iptoolbox
Classifier: Topic :: Internet
Classifier: Natural Language :: English
Classifier: License :: OSI Approved :: MIT License
Classifier: Development Status :: 1 - Planning
Classifier: Operating System :: POSIX
Classifier: Operating System :: Unix
Classifier: Operating System :: Microsoft
Classifier: Operating System :: MacOS
Classifier: Operating System :: BeOS
Classifier: Programming Language :: Python :: 3.6
Classifier: Programming Language :: Python :: 3.7
Classifier: Programming Language :: Python :: 3.8
Classifier: Programming Language :: Python :: 3.9
Classifier: Programming Language :: Python :: 3.10
Requires-Python: >=3.6
License-File: LICENSE
